stream_buffer/__init__.py
stream_buffer/buffer.py
stream_buffer-0.1.0.dist-info/METADATA
stream_buffer-0.1.0.dist-info/WHEEL
stream_buffer-0.1.0.dist-info/top_level.txt
stream_buffer-0.1.0.dist-info/RECORD
