Metadata-Version: 2.4
Name: stream-buffer
Version: 0.1.0
Summary: A lightweight circular buffer for handling stream data with fast appending and retrieval.
Project-URL: Homepage, https://github.com/blazestorm001/stream-buffer
Requires-Python: >=3.8
Requires-Dist: numpy>=1.18.5
Provides-Extra: dev
Requires-Dist: pytest; extra == "dev"
